Workbook

Sheet 01_Source_Data
A1: Greggs plc – FP&A Budget & Forecast Analysis
A3: Metric | B3: H1 2025 Actual (£m) | C3: FY2025 Actual (£m) | D3: H1 2026 Actual (£m)
A4: Revenue | B4: 1027.7 | C4: 2151.2 | D4: 1101.5
A5: Cost of Sales | B5: 396 | C5: 829.1 | D5: 418.4
A6: Gross Profit | B6: 631.7 | C6: 1322.1 | D6: 683.1
A7: Distribution & Selling Costs | B7: 510.8 | C7: 1036.3 | D7: 539.9
A8: Administrative Expenses | B8: 50.5 | C8: 102.1 | D8: 56.7
A9: Operating Profit | B9: 70.4 | C9: 183.7 | D9: 86.5
A10: Finance Income | B10: 1.3 | C10: 1.8 | D10: 0.8
A11: Finance Expense | B11: 8.2 | C11: 18.1 | D11: 11.3
A12: Profit Before Tax | B12: 63.5 | C12: 167.4 | D12: 76
A16: Operating KPI | B16: H1 2026
A17: Total Sales Growth | B17: 0.072
A18: Company-managed LFL Sales Growth | B18: 0.021
A19: Franchise LFL Sales Growth | B19: 0.013
A20: Net New Shops | B20: 34
A21: Total Shops | B21: 2773
A22: Structural Cost Savings Delivered | B22: £7m
A23: Structural Cost Savings FY Target | B23: £11m
A24: FY2026 Expected Capex | B24: £180m

Sheet 02_Budget
A1: Greggs plc – FY2026 Simulated Budget
A3: Metric | B3: FY2025 Actual (£m) | C3: FY2026 Budget Assumption | D3: FY2026 Budget (£m)
A4: Revenue | B4: ='01_Source_Data'!C4 -> 2151.2 | C4: 0.06 | D4: =B4*(1+C4) -> 2280.272
A5: Cost of Sales | B5: ='01_Source_Data'!C5 -> 829.1 | C5: 38.5% of Revenue | D5: =D4*38.5% -> 877.90472
A6: Gross Profit | B6: ='01_Source_Data'!C6 -> 1322.1 | C6: Calculated | D6: =D4-D5 -> 1402.3673
A7: Distribution & Selling Costs | B7: ='01_Source_Data'!C7 -> 1036.3 | C7: 0.05 | D7: =B7*(1+C7) -> 1088.115
A8: Administrative Expenses | B8: ='01_Source_Data'!C8 -> 102.1 | C8: 0.04 | D8: =B8*(1+C8) -> 106.184
A9: Operating Profit | B9: ='01_Source_Data'!C9 -> 183.7 | C9: Calculated | D9: =D6-D7-D8 -> 208.06828
A10: Operating Margin | B10: =B9/B4 -> 0.085394199 | C10: Calculated | D10: =D9/D4 -> 0.091247132

Sheet 03_Actual_vs_Budget
A1: Greggs plc – H1 2026 Actual vs Budget
A3: Metric | B3: H1 2026 Budget (£m) | C3: H1 2026 Actual (£m) | D3: Variance (£m) | E3: Variance (%) | F3: Status
A4: Revenue | B4: ='02_Budget'!D4/2 -> 1140.136 | C4: ='01_Source_Data'!D4 -> 1101.5 | D4: =C4-B4 -> -38.636 | E4: =D4/B4 -> -0.033887185 | F4: =IF(D4>0,"Favourable",IF(D4<0,"Unfavourable","On Budget")) -> Unfavourable
A5: Cost of Sales | B5: ='02_Budget'!D5/2 -> 438.95236 | C5: ='01_Source_Data'!D5 -> 418.4 | D5: =B5-C5 -> 20.55236 | E5: =D5/B5 -> 0.046821391 | F5: =IF(D5>0,"Favourable",IF(D5<0,"Unfavourable","On Budget")) -> Favourable
A6: Gross Profit | B6: =B4-B5 -> 701.18364 | C6: ='01_Source_Data'!D6 -> 683.1 | D6: =C6-B6 -> -18.08364 | E6: =D6/B6 -> -0.025790162 | F6: =IF(D6>0,"Favourable",IF(D6<0,"Unfavourable","On Budget")) -> Unfavourable
A7: Distribution & Selling Costs | B7: ='02_Budget'!D7/2 -> 544.0575 | C7: ='01_Source_Data'!D7 -> 539.9 | D7: =B7-C7 -> 4.1575 | E7: =D7/B7 -> 0.0076416555 | F7: =IF(D7>0,"Favourable",IF(D7<0,"Unfavourable","On Budget")) -> Favourable
A8: Administrative Expenses | B8: ='02_Budget'!D8/2 -> 53.092 | C8: ='01_Source_Data'!D8 -> 56.7 | D8: =B8-C8 -> -3.608 | E8: =D8/B8 -> -0.067957508 | F8: =IF(D8>0,"Favourable",IF(D8<0,"Unfavourable","On Budget")) -> Unfavourable
A9: Operating Profit | B9: =B6-B7-B8 -> 104.03414 | C9: ='01_Source_Data'!D9 -> 86.5 | D9: =C9-B9 -> -17.53414 | E9: =D9/B9 -> -0.16854217 | F9: =IF(D9>0,"Favourable",IF(D9<0,"Unfavourable","On Budget")) -> Unfavourable
A10: Operating Margin | B10: =B9/B4 -> 0.091247132 | C10: =C9/C4 -> 0.078529278 | D10: =C10-B10 -> -0.012717854 | E10: N/A | F10: =IF(D10>0,"Favourable",IF(D10<0,"Unfavourable","On Budget")) -> Unfavourable
A14: Budget phasing assumption: H1 budget represents 50% of the simulated FY2026 budget. This simplified phasing assumption is used for portfolio analysis and does not represent Greggs' internal budgeting methodology.

Sheet 04_Variance_Analysis
A1: Greggs plc – H1 2026 Variance Analysis
A3: Metric | B3: Budget (£m) | C3: Actual (£m) | D3: Variance (£m) | E3: Variance (%) | F3: F/U | G3: Management Explanation
A4: Revenue | B4: ='03_Actual_vs_Budget'!B4 -> 1140.136 | C4: ='03_Actual_vs_Budget'!C4 -> 1101.5 | D4: ='03_Actual_vs_Budget'!D4 -> -38.636 | E4: ='03_Actual_vs_Budget'!E4 -> -0.033887185 | F4: ='03_Actual_vs_Budget'!F4 -> Unfavourable
A5: Cost of Sales | B5: ='03_Actual_vs_Budget'!B5 -> 438.95236 | C5: ='03_Actual_vs_Budget'!C5 -> 418.4 | D5: ='03_Actual_vs_Budget'!D5 -> 20.55236 | E5: ='03_Actual_vs_Budget'!E5 -> 0.046821391 | F5: ='03_Actual_vs_Budget'!F5 -> Favourable
A6: Gross Profit | B6: ='03_Actual_vs_Budget'!B6 -> 701.18364 | C6: ='03_Actual_vs_Budget'!C6 -> 683.1 | D6: ='03_Actual_vs_Budget'!D6 -> -18.08364 | E6: ='03_Actual_vs_Budget'!E6 -> -0.025790162 | F6: ='03_Actual_vs_Budget'!F6 -> Unfavourable
A7: Distribution & Selling Costs | B7: ='03_Actual_vs_Budget'!B7 -> 544.0575 | C7: ='03_Actual_vs_Budget'!C7 -> 539.9 | D7: ='03_Actual_vs_Budget'!D7 -> 4.1575 | E7: ='03_Actual_vs_Budget'!E7 -> 0.0076416555 | F7: ='03_Actual_vs_Budget'!F7 -> Favourable
A8: Administrative Expenses | B8: ='03_Actual_vs_Budget'!B8 -> 53.092 | C8: ='03_Actual_vs_Budget'!C8 -> 56.7 | D8: ='03_Actual_vs_Budget'!D8 -> -3.608 | E8: ='03_Actual_vs_Budget'!E8 -> -0.067957508 | F8: ='03_Actual_vs_Budget'!F8 -> Unfavourable
A9: Operating Profit | B9: ='03_Actual_vs_Budget'!B9 -> 104.03414 | C9: ='03_Actual_vs_Budget'!C9 -> 86.5 | D9: ='03_Actual_vs_Budget'!D9 -> -17.53414 | E9: ='03_Actual_vs_Budget'!E9 -> -0.16854217 | F9: ='03_Actual_vs_Budget'!F9 -> Unfavourable

Sheet 05_Forecast
A1: Greggs plc – FY2026 Revised Forecast
A3: Metric | B3: FY2026 Budget (£m) | C3: H1 2026 Actual (£m) | D3: H2 2026 Forecast (£m) | E3: FY2026 Revised Forecast (£m) | F3: Forecast vs Budget (£m) | G3: Forecast vs Budget (%)
A4: Revenue | B4: ='02_Budget'!D4 -> 2280.272 | C4: ='03_Actual_vs_Budget'!C4 -> 1101.5 | D4: =C4*(1+$B$17) -> 1156.575 | E4: =C4+D4 -> 2258.075 | F4: =E4-B4 -> -22.197 | G4: =F4/B4 -> -0.009734365
A5: Cost of Sales | B5: ='02_Budget'!D5 -> 877.90472 | C5: ='03_Actual_vs_Budget'!C5 -> 418.4 | D5: =D4*B18 -> 439.4985 | E5: =C5+D5 -> 857.8985 | F5: =B5-E5 -> 20.00622 | G5: =F5/B5 -> 0.022788601
A6: Gross Profit | B6: ='02_Budget'!D6 -> 1402.3673 | C6: ='03_Actual_vs_Budget'!C6 -> 683.1 | D6: =D4-D5 -> 717.0765 | E6: =C6+D6 -> 1400.1765 | F6: =E6-B6 -> -2.19078 | G6: =F6/B6 -> -0.0015622013
A7: Distribution & Selling Costs | B7: ='02_Budget'!D7 -> 1088.115 | C7: ='03_Actual_vs_Budget'!C7 -> 539.9 | D7: =C7*(1+$B$19) -> 556.097 | E7: =C7+D7 -> 1095.997 | F7: =B7-E7 -> -7.882 | G7: =F7/B7 -> -0.0072437196
A8: Administrative Expenses | B8: ='02_Budget'!D8 -> 106.184 | C8: ='03_Actual_vs_Budget'!C8 -> 56.7 | D8: =C8*(1+$B$20) -> 57.834 | E8: =C8+D8 -> 114.534 | F8: =B8-E8 -> -8.35 | G8: =F8/B8 -> -0.078637083
A9: Operating Profit | B9: ='02_Budget'!D9 -> 208.06828 | C9: ='03_Actual_vs_Budget'!C9 -> 86.5 | D9: =D6-D7-D8 -> 103.1455 | E9: =C9+D9 -> 189.6455 | F9: =E9-B9 -> -18.42278 | G9: =F9/B9 -> -0.088541992
A10: Operating Margin | B10: ='02_Budget'!D10 -> 0.091247132 | C10: ='03_Actual_vs_Budget'!C10 -> 0.078529278 | D10: =D9/D4 -> 0.089181852 | E10: =E9/E4 -> 0.083985474 | F10: =E10-B10 -> -0.0072616576 | G10: N/A
A16: Forecast Assumption | B16: Value
A17: H2 Revenue Growth vs H1 | B17: 0.05
A18: H2 Cost of Sales % of Revenue | B18: 0.38
A19: H2 Distribution & Selling Cost Growth vs H1 | B19: 0.03
A20: H2 Administrative Expense Growth vs H1 | B20: 0.02

Sheet 06_Dashboard
A1: Greggs plc – FY2026 FP&A Performance Dashboard
A3: Revenue Forecast £m | B3: Operating Profit Forecast £m | C3: Operating Margin | D3: Revenue vs Budget
A4: ='05_Forecast'!E4 -> 2258.075 | B4: ='05_Forecast'!E9 -> 189.6455 | C4: ='05_Forecast'!E10 -> 0.083985474 | D4: ='05_Forecast'!G4 -> -0.009734365
A7: Metric | B7: FY2026 Budget | C7: Revised Forecast
A8: Revenue | B8: ='05_Forecast'!B4 -> 2280.272 | C8: ='05_Forecast'!E4 -> 2258.075
A9: Gross Profit | B9: ='05_Forecast'!B6 -> 1402.3673 | C9: ='05_Forecast'!E6 -> 1400.1765
A10: Operating Profit | B10: ='05_Forecast'!B9 -> 208.06828 | C10: ='05_Forecast'!E9 -> 189.6455
A17: Key Forecast Variances
A19: Metric | B19: Forecast vs Budget | C19: Status
A20: Revenue | B20: ='05_Forecast'!G4 -> -0.009734365 | C20: =IF(B20>0,"Favourable",IF(B20<0,"Unfavourable","On Budget")) -> Unfavourable
A21: Cost of Sales | B21: ='05_Forecast'!G5 -> 0.022788601 | C21: =IF(B21>0,"Favourable",IF(B21<0,"Unfavourable","On Budget")) -> Favourable
A22: Gross Profit | B22: ='05_Forecast'!G6 -> -0.0015622013 | C22: =IF(B22>0,"Favourable",IF(B22<0,"Unfavourable","On Budget")) -> Unfavourable
A23: Distribution & Selling Costs | B23: ='05_Forecast'!G7 -> -0.0072437196 | C23: =IF(B23>0,"Favourable",IF(B23<0,"Unfavourable","On Budget")) -> Unfavourable
A24: Administrative Expenses | B24: ='05_Forecast'!G8 -> -0.078637083 | C24: =IF(B24>0,"Favourable",IF(B24<0,"Unfavourable","On Budget")) -> Unfavourable
A25: Operating Profit | B25: ='05_Forecast'!G9 -> -0.088541992 | C25: =IF(B25>0,"Favourable",IF(B25<0,"Unfavourable","On Budget")) -> Unfavourable
A28: Metric | B28: H1 Budget | C28: H1 Actual
A29: Revenue | B29: ='03_Actual_vs_Budget'!B4 -> 1140.136 | C29: ='03_Actual_vs_Budget'!C4 -> 1101.5
A30: Gross Profit | B30: ='03_Actual_vs_Budget'!B6 -> 701.18364 | C30: ='03_Actual_vs_Budget'!C6 -> 683.1
A31: Operating Profit | B31: ='03_Actual_vs_Budget'!B9 -> 104.03414 | C31: ='03_Actual_vs_Budget'!C9 -> 86.5

Sheet 07_Management_Commentary
A1: Greggs plc – FY2026 FP&A Management Commentary
A3: 1. Executive Summary
A4: Greggs delivered positive year-on-year growth in H1 2026, with sales increasing 7.2% and operating profit rising 22.9%. However, against the simulated FP&A budget, H1 revenue was approximately £38.6m below plan and operating profit was approximately £17.5m below plan. Following the H1 performance review, the FY2026 revised forecast indicates revenue of approximately £2,258.1m and operating profit of £189.6m, both below the original simulated budget.
A6: 2. H1 2026 Performance vs Budget
A7: H1 revenue of £1,101.5m was approximately £38.6m below the simulated budget, despite positive year-on-year sales growth and continued shop expansion. Cost of sales was approximately £20.6m favourable to budget, partially offsetting the revenue shortfall. Distribution and selling costs were also slightly favourable, while administrative expenses were approximately £3.6m above budget. Overall, operating profit of £86.5m was approximately £17.5m below the simulated H1 budget.
A9: 3. FY2026 Revised Forecast
A10: Following the H1 review, FY2026 revenue is forecast at approximately £2,258.1m compared with the original simulated budget of £2,280.3m. Operating profit is forecast at approximately £189.6m versus £208.1m budget, representing an unfavourable variance of approximately 8.9%. Operating margin is forecast at approximately 8.40%, below the 9.12% budget margin. The revised forecast therefore indicates continued profitability but weaker performance than originally budgeted.
A12: 4. Key Risks & Management Actions
A13: Key risks include weaker-than-budgeted revenue growth, continued cost inflation and higher operating costs associated with Greggs' investment and expansion programme. Management should closely monitor like-for-like sales, shop performance, administrative expenses and operating margin during H2. Continued focus on structural cost savings and operational efficiency could help mitigate margin pressure, while forecast assumptions should be reviewed regularly as new trading information becomes available.
A15: Portfolio note: Actual financial information is sourced from Greggs plc's published financial reports. Budget and forecast figures are independently developed assumptions for educational and portfolio purposes and do not represent Greggs plc's internal budgets or forecasts.
